getSequence/__init__.py
getSequence/_version.py
getSequence/get_sequence.py
getSequence/getseq.py
getSequence/getsequence_exceptions.py
getSequence/scripts/__init__.py
getSequence/scripts/getseq.py
getSequence/tests/__init__.py
getSequence/tests/test_getSequence.py
getSequence-2.2.1.dist-info/LICENSE
getSequence-2.2.1.dist-info/METADATA
getSequence-2.2.1.dist-info/WHEEL
getSequence-2.2.1.dist-info/entry_points.txt
getSequence-2.2.1.dist-info/top_level.txt
getSequence-2.2.1.dist-info/RECORD
