Metadata-Version: 2.1
Name: getSequence
Version: 2.2.1
Summary: A tool to get a protein sequences from Uniprot using a CLI or in Python.
Author-email: Ryan Emenecker <remenecker@wustl.edu>
License: MIT
Requires-Python: >=3.8
License-File: LICENSE
Requires-Dist: urllib3
Requires-Dist: requests
Requires-Dist: protfasta
Provides-Extra: test
Requires-Dist: pytest>=6.1.2; extra == "test"
